<?xml version="1.0" encoding="ISO-8859-1"?>
<formulaset format="3.0">
	<formulaset-name>Scrolls - Travel</formulaset-name>
	<formulaset-categories>
		<formulaset-category>Scrolls</formulaset-category>
	</formulaset-categories>
	<item>
		<item-name>Aughendell Travel</item-name>
		<item-icon>icon_formula_sc_01_08_11.png</item-icon>
		<item-batchqty>2</item-batchqty>
		<item-attributes>
			<item-attribute type="equipSlot">All</item-attribute>
			<item-attribute type="bulk">1</item-attribute>
			<item-attribute type="range">Self Only</item-attribute>
			<item-attribute type="recycle">30</item-attribute>
			<item-attribute type="castDelay">70</item-attribute>
			<item-attribute type="effectDescription">Teleport to a city, even with a portable cargo disk equipped.</item-attribute>
		</item-attributes>
		<item-keywords>
		</item-keywords>
		<tier>
			<tier-name>Aughendell Travel</tier-name>
			<tier-lvl name="">5</tier-lvl>
			<tier-desc>A rolled up piece of parchment, covered with strange lettering and faintly glowing runes. The parchment fairly hums with imbued power.</tier-desc>
			<tier-allowedtechniques>0</tier-allowedtechniques>
			<tier-attributes>
				<tier-attribute type="hoardValue">640</tier-attribute>
				<tier-attribute type="reqCurrentAdvLevel">Current Adventure Level (90)</tier-attribute>
			</tier-attributes>
			<tier-keywords>
				<tier-keyword>tier_5</tier-keyword>
			</tier-keywords>
			<resources>
				<resource>
					<resource-name>Aughendell Travel Token</resource-name>
					<resource-skill>Scribing</resource-skill>
					<resource-units>1</resource-units>
					<resource-min amount="1">950</resource-min>
					<resource-opt amount="1">1250</resource-opt>
				</resource>
				<resource>
					<resource-name>Silver Papyrus Sheet</resource-name>
					<resource-skill>Scribing</resource-skill>
					<resource-units>1</resource-units>
					<resource-min amount="5">950</resource-min>
					<resource-opt amount="2">1250</resource-opt>
				</resource>
				<resource>
					<resource-name>Swift Feet V</resource-name>
					<resource-skill>Scribing</resource-skill>
					<resource-units>1</resource-units>
					<resource-min amount="1">950</resource-min>
					<resource-opt amount="1">1250</resource-opt>
				</resource>
				<resource>
					<resource-name>Shining Essence Orb</resource-name>
					<resource-skill>Scribing</resource-skill>
					<resource-units>1</resource-units>
					<resource-min amount="3">950</resource-min>
					<resource-opt amount="1">1250</resource-opt>
				</resource>
			</resources>
		</tier>
	</item>
	<item>
		<item-name>Chiconis Travel</item-name>
		<item-icon>icon_formula_sc_01_08_11.png</item-icon>
		<item-batchqty>2</item-batchqty>
		<item-attributes>
			<item-attribute type="equipSlot">All</item-attribute>
			<item-attribute type="bulk">1</item-attribute>
			<item-attribute type="range">Self Only</item-attribute>
			<item-attribute type="recycle">30</item-attribute>
			<item-attribute type="castDelay">70</item-attribute>
			<item-attribute type="effectDescription">Teleport to a city, even with a portable cargo disk equipped.</item-attribute>
		</item-attributes>
		<item-keywords>
		</item-keywords>
		<tier>
			<tier-name>Chiconis Travel</tier-name>
			<tier-lvl name="">2</tier-lvl>
			<tier-desc>A rolled up piece of parchment, covered with strange lettering and faintly glowing runes. The parchment fairly hums with imbued power.</tier-desc>
			<tier-allowedtechniques>0</tier-allowedtechniques>
			<tier-attributes>
				<tier-attribute type="hoardValue">80</tier-attribute>
				<tier-attribute type="reqCurrentAdvLevel">Current Adventure Level (30)</tier-attribute>
			</tier-attributes>
			<tier-keywords>
				<tier-keyword>tier_2</tier-keyword>
			</tier-keywords>
			<resources>
				<resource>
					<resource-name>Chiconis Travel Token</resource-name>
					<resource-skill>Scribing</resource-skill>
					<resource-units>1</resource-units>
					<resource-min amount="1">350</resource-min>
					<resource-opt amount="1">575</resource-opt>
				</resource>
				<resource>
					<resource-name>White Papyrus Sheet</resource-name>
					<resource-skill>Scribing</resource-skill>
					<resource-units>1</resource-units>
					<resource-min amount="5">350</resource-min>
					<resource-opt amount="2">575</resource-opt>
				</resource>
				<resource>
					<resource-name>Swift Feet II</resource-name>
					<resource-skill>Scribing</resource-skill>
					<resource-units>1</resource-units>
					<resource-min amount="1">350</resource-min>
					<resource-opt amount="1">575</resource-opt>
				</resource>
				<resource>
					<resource-name>Pale Essence Orb</resource-name>
					<resource-skill>Scribing</resource-skill>
					<resource-units>1</resource-units>
					<resource-min amount="3">350</resource-min>
					<resource-opt amount="1">575</resource-opt>
				</resource>
			</resources>
		</tier>
	</item>
	<item>
		<item-name>Dalimond Travel</item-name>
		<item-icon>icon_formula_sc_01_08_11.png</item-icon>
		<item-batchqty>2</item-batchqty>
		<item-attributes>
			<item-attribute type="equipSlot">All</item-attribute>
			<item-attribute type="bulk">1</item-attribute>
			<item-attribute type="range">Self Only</item-attribute>
			<item-attribute type="recycle">30</item-attribute>
			<item-attribute type="castDelay">70</item-attribute>
			<item-attribute type="effectDescription">Teleport to a city, even with a portable cargo disk equipped.</item-attribute>
		</item-attributes>
		<item-keywords>
		</item-keywords>
		<tier>
			<tier-name>Dalimond Travel</tier-name>
			<tier-lvl name="">2</tier-lvl>
			<tier-desc>A rolled up piece of parchment, covered with strange lettering and faintly glowing runes. The parchment fairly hums with imbued power.</tier-desc>
			<tier-allowedtechniques>0</tier-allowedtechniques>
			<tier-attributes>
				<tier-attribute type="hoardValue">80</tier-attribute>
				<tier-attribute type="reqCurrentAdvLevel">Current Adventure Level (30)</tier-attribute>
			</tier-attributes>
			<tier-keywords>
				<tier-keyword>tier_2</tier-keyword>
			</tier-keywords>
			<resources>
				<resource>
					<resource-name>Dalimond Travel Token</resource-name>
					<resource-skill>Scribing</resource-skill>
					<resource-units>1</resource-units>
					<resource-min amount="1">350</resource-min>
					<resource-opt amount="1">575</resource-opt>
				</resource>
				<resource>
					<resource-name>White Papyrus Sheet</resource-name>
					<resource-skill>Scribing</resource-skill>
					<resource-units>1</resource-units>
					<resource-min amount="5">350</resource-min>
					<resource-opt amount="2">575</resource-opt>
				</resource>
				<resource>
					<resource-name>Swift Feet II</resource-name>
					<resource-skill>Scribing</resource-skill>
					<resource-units>1</resource-units>
					<resource-min amount="1">350</resource-min>
					<resource-opt amount="1">575</resource-opt>
				</resource>
				<resource>
					<resource-name>Pale Essence Orb</resource-name>
					<resource-skill>Scribing</resource-skill>
					<resource-units>1</resource-units>
					<resource-min amount="3">350</resource-min>
					<resource-opt amount="1">575</resource-opt>
				</resource>
			</resources>
		</tier>
	</item>
	<item>
		<item-name>Dralk Travel</item-name>
		<item-icon>icon_formula_sc_01_08_11.png</item-icon>
		<item-batchqty>2</item-batchqty>
		<item-attributes>
			<item-attribute type="equipSlot">All</item-attribute>
			<item-attribute type="bulk">1</item-attribute>
			<item-attribute type="range">Self Only</item-attribute>
			<item-attribute type="recycle">30</item-attribute>
			<item-attribute type="castDelay">70</item-attribute>
			<item-attribute type="effectDescription">Teleport to a city, even with a portable cargo disk equipped.</item-attribute>
		</item-attributes>
		<item-keywords>
		</item-keywords>
		<tier>
			<tier-name>Dralk Travel</tier-name>
			<tier-lvl name="">4</tier-lvl>
			<tier-desc>A rolled up piece of parchment, covered with strange lettering and faintly glowing runes. The parchment fairly hums with imbued power.</tier-desc>
			<tier-allowedtechniques>0</tier-allowedtechniques>
			<tier-attributes>
				<tier-attribute type="hoardValue">320</tier-attribute>
				<tier-attribute type="reqCurrentAdvLevel">Current Adventure Level (70)</tier-attribute>
			</tier-attributes>
			<tier-keywords>
				<tier-keyword>tier_4</tier-keyword>
			</tier-keywords>
			<resources>
				<resource>
					<resource-name>Dralk Travel Token</resource-name>
					<resource-skill>Scribing</resource-skill>
					<resource-units>1</resource-units>
					<resource-min amount="1">750</resource-min>
					<resource-opt amount="1">1025</resource-opt>
				</resource>
				<resource>
					<resource-name>Rose Papyrus Sheet</resource-name>
					<resource-skill>Scribing</resource-skill>
					<resource-units>1</resource-units>
					<resource-min amount="5">750</resource-min>
					<resource-opt amount="2">1025</resource-opt>
				</resource>
				<resource>
					<resource-name>Swift Feet IV</resource-name>
					<resource-skill>Scribing</resource-skill>
					<resource-units>1</resource-units>
					<resource-min amount="1">750</resource-min>
					<resource-opt amount="1">1025</resource-opt>
				</resource>
				<resource>
					<resource-name>Bright Essence Orb</resource-name>
					<resource-skill>Scribing</resource-skill>
					<resource-units>1</resource-units>
					<resource-min amount="3">750</resource-min>
					<resource-opt amount="1">1025</resource-opt>
				</resource>
			</resources>
		</tier>
	</item>
	<item>
		<item-name>Feladan Travel</item-name>
		<item-icon>icon_formula_sc_01_08_11.png</item-icon>
		<item-batchqty>2</item-batchqty>
		<item-attributes>
			<item-attribute type="equipSlot">All</item-attribute>
			<item-attribute type="bulk">1</item-attribute>
			<item-attribute type="range">Self Only</item-attribute>
			<item-attribute type="recycle">30</item-attribute>
			<item-attribute type="castDelay">70</item-attribute>
			<item-attribute type="effectDescription">Teleport to a city, even with a portable cargo disk equipped.</item-attribute>
		</item-attributes>
		<item-keywords>
		</item-keywords>
		<tier>
			<tier-name>Feladan Travel</tier-name>
			<tier-lvl name="">4</tier-lvl>
			<tier-desc>A rolled up piece of parchment, covered with strange lettering and faintly glowing runes. The parchment fairly hums with imbued power.</tier-desc>
			<tier-allowedtechniques>0</tier-allowedtechniques>
			<tier-attributes>
				<tier-attribute type="hoardValue">320</tier-attribute>
				<tier-attribute type="reqCurrentAdvLevel">Current Adventure Level (70)</tier-attribute>
			</tier-attributes>
			<tier-keywords>
				<tier-keyword>tier_4</tier-keyword>
			</tier-keywords>
			<resources>
				<resource>
					<resource-name>Feladan Travel Token</resource-name>
					<resource-skill>Scribing</resource-skill>
					<resource-units>1</resource-units>
					<resource-min amount="1">750</resource-min>
					<resource-opt amount="1">1025</resource-opt>
				</resource>
				<resource>
					<resource-name>Rose Papyrus Sheet</resource-name>
					<resource-skill>Scribing</resource-skill>
					<resource-units>1</resource-units>
					<resource-min amount="5">750</resource-min>
					<resource-opt amount="2">1025</resource-opt>
				</resource>
				<resource>
					<resource-name>Swift Feet IV</resource-name>
					<resource-skill>Scribing</resource-skill>
					<resource-units>1</resource-units>
					<resource-min amount="1">750</resource-min>
					<resource-opt amount="1">1025</resource-opt>
				</resource>
				<resource>
					<resource-name>Bright Essence Orb</resource-name>
					<resource-skill>Scribing</resource-skill>
					<resource-units>1</resource-units>
					<resource-min amount="3">750</resource-min>
					<resource-opt amount="1">1025</resource-opt>
				</resource>
			</resources>
		</tier>
	</item>
	<item>
		<item-name>Kion Travel</item-name>
		<item-icon>icon_formula_sc_01_08_11.png</item-icon>
		<item-batchqty>2</item-batchqty>
		<item-attributes>
			<item-attribute type="equipSlot">All</item-attribute>
			<item-attribute type="bulk">1</item-attribute>
			<item-attribute type="range">Self Only</item-attribute>
			<item-attribute type="recycle">30</item-attribute>
			<item-attribute type="castDelay">70</item-attribute>
			<item-attribute type="effectDescription">Teleport to a city, even with a portable cargo disk equipped.</item-attribute>
		</item-attributes>
		<item-keywords>
		</item-keywords>
		<tier>
			<tier-name>Kion Travel</tier-name>
			<tier-lvl name="">1</tier-lvl>
			<tier-desc>A rolled up piece of parchment, covered with strange lettering and faintly glowing runes. The parchment fairly hums with imbued power.</tier-desc>
			<tier-allowedtechniques>0</tier-allowedtechniques>
			<tier-attributes>
				<tier-attribute type="hoardValue">40</tier-attribute>
				<tier-attribute type="reqCurrentAdvLevel">Current Adventure Level (15)</tier-attribute>
			</tier-attributes>
			<tier-keywords>
				<tier-keyword>tier_1</tier-keyword>
			</tier-keywords>
			<resources>
				<resource>
					<resource-name>Kion Travel Token</resource-name>
					<resource-skill>Scribing</resource-skill>
					<resource-units>1</resource-units>
					<resource-min amount="1">150</resource-min>
					<resource-opt amount="1">350</resource-opt>
				</resource>
				<resource>
					<resource-name>Common Papyrus Sheet</resource-name>
					<resource-skill>Scribing</resource-skill>
					<resource-units>1</resource-units>
					<resource-min amount="5">150</resource-min>
					<resource-opt amount="2">350</resource-opt>
				</resource>
				<resource>
					<resource-name>Swift Feet I</resource-name>
					<resource-skill>Scribing</resource-skill>
					<resource-units>1</resource-units>
					<resource-min amount="1">150</resource-min>
					<resource-opt amount="1">350</resource-opt>
				</resource>
				<resource>
					<resource-name>Dim Essence Orb</resource-name>
					<resource-skill>Scribing</resource-skill>
					<resource-units>1</resource-units>
					<resource-min amount="3">150</resource-min>
					<resource-opt amount="1">350</resource-opt>
				</resource>
			</resources>
		</tier>
	</item>
	<item>
		<item-name>Kirasanct Travel</item-name>
		<item-icon>icon_formula_sc_01_08_11.png</item-icon>
		<item-batchqty>2</item-batchqty>
		<item-attributes>
			<item-attribute type="equipSlot">All</item-attribute>
			<item-attribute type="bulk">1</item-attribute>
			<item-attribute type="range">Self Only</item-attribute>
			<item-attribute type="recycle">30</item-attribute>
			<item-attribute type="castDelay">70</item-attribute>
			<item-attribute type="effectDescription">Teleport to a city, even with a portable cargo disk equipped.</item-attribute>
		</item-attributes>
		<item-keywords>
		</item-keywords>
		<tier>
			<tier-name>Kirasanct Travel</tier-name>
			<tier-lvl name="">4</tier-lvl>
			<tier-desc>A rolled up piece of parchment, covered with strange lettering and faintly glowing runes. The parchment fairly hums with imbued power.</tier-desc>
			<tier-allowedtechniques>0</tier-allowedtechniques>
			<tier-attributes>
				<tier-attribute type="hoardValue">320</tier-attribute>
				<tier-attribute type="reqCurrentAdvLevel">Current Adventure Level (70)</tier-attribute>
			</tier-attributes>
			<tier-keywords>
				<tier-keyword>tier_4</tier-keyword>
			</tier-keywords>
			<resources>
				<resource>
					<resource-name>Kirasanct Travel Token</resource-name>
					<resource-skill>Scribing</resource-skill>
					<resource-units>1</resource-units>
					<resource-min amount="1">750</resource-min>
					<resource-opt amount="1">1025</resource-opt>
				</resource>
				<resource>
					<resource-name>Rose Papyrus Sheet</resource-name>
					<resource-skill>Scribing</resource-skill>
					<resource-units>1</resource-units>
					<resource-min amount="5">750</resource-min>
					<resource-opt amount="2">1025</resource-opt>
				</resource>
				<resource>
					<resource-name>Swift Feet IV</resource-name>
					<resource-skill>Scribing</resource-skill>
					<resource-units>1</resource-units>
					<resource-min amount="1">750</resource-min>
					<resource-opt amount="1">1025</resource-opt>
				</resource>
				<resource>
					<resource-name>Bright Essence Orb</resource-name>
					<resource-skill>Scribing</resource-skill>
					<resource-units>1</resource-units>
					<resource-min amount="3">750</resource-min>
					<resource-opt amount="1">1025</resource-opt>
				</resource>
			</resources>
		</tier>
	</item>
	<item>
		<item-name>Mahagra Travel</item-name>
		<item-icon>icon_formula_sc_01_08_11.png</item-icon>
		<item-batchqty>2</item-batchqty>
		<item-attributes>
			<item-attribute type="equipSlot">All</item-attribute>
			<item-attribute type="bulk">1</item-attribute>
			<item-attribute type="range">Self Only</item-attribute>
			<item-attribute type="recycle">30</item-attribute>
			<item-attribute type="castDelay">70</item-attribute>
			<item-attribute type="effectDescription">Teleport to a city, even with a portable cargo disk equipped.</item-attribute>
		</item-attributes>
		<item-keywords>
		</item-keywords>
		<tier>
			<tier-name>Mahagra Travel</tier-name>
			<tier-lvl name="">3</tier-lvl>
			<tier-desc>A rolled up piece of parchment, covered with strange lettering and faintly glowing runes. The parchment fairly hums with imbued power.</tier-desc>
			<tier-allowedtechniques>0</tier-allowedtechniques>
			<tier-attributes>
				<tier-attribute type="hoardValue">160</tier-attribute>
				<tier-attribute type="reqCurrentAdvLevel">Current Adventure Level (50)</tier-attribute>
			</tier-attributes>
			<tier-keywords>
				<tier-keyword>tier_3</tier-keyword>
			</tier-keywords>
			<resources>
				<resource>
					<resource-name>Mahagra Travel Token</resource-name>
					<resource-skill>Scribing</resource-skill>
					<resource-units>1</resource-units>
					<resource-min amount="1">550</resource-min>
					<resource-opt amount="1">800</resource-opt>
				</resource>
				<resource>
					<resource-name>Azure Papyrus Sheet</resource-name>
					<resource-skill>Scribing</resource-skill>
					<resource-units>1</resource-units>
					<resource-min amount="5">550</resource-min>
					<resource-opt amount="2">800</resource-opt>
				</resource>
				<resource>
					<resource-name>Swift Feet III</resource-name>
					<resource-skill>Scribing</resource-skill>
					<resource-units>1</resource-units>
					<resource-min amount="1">550</resource-min>
					<resource-opt amount="1">800</resource-opt>
				</resource>
				<resource>
					<resource-name>Glowing Essence Orb</resource-name>
					<resource-skill>Scribing</resource-skill>
					<resource-units>1</resource-units>
					<resource-min amount="3">550</resource-min>
					<resource-opt amount="1">800</resource-opt>
				</resource>
			</resources>
		</tier>
	</item>
	<item>
		<item-name>New Rachival Travel</item-name>
		<item-icon>icon_formula_sc_01_08_11.png</item-icon>
		<item-batchqty>2</item-batchqty>
		<item-attributes>
			<item-attribute type="equipSlot">All</item-attribute>
			<item-attribute type="bulk">1</item-attribute>
			<item-attribute type="range">Self Only</item-attribute>
			<item-attribute type="recycle">30</item-attribute>
			<item-attribute type="castDelay">70</item-attribute>
			<item-attribute type="effectDescription">Teleport to a city, even with a portable cargo disk equipped.</item-attribute>
		</item-attributes>
		<item-keywords>
		</item-keywords>
		<tier>
			<tier-name>New Rachival Travel</tier-name>
			<tier-lvl name="">3</tier-lvl>
			<tier-desc>A rolled up piece of parchment, covered with strange lettering and faintly glowing runes. The parchment fairly hums with imbued power.</tier-desc>
			<tier-allowedtechniques>0</tier-allowedtechniques>
			<tier-attributes>
				<tier-attribute type="hoardValue">160</tier-attribute>
				<tier-attribute type="reqCurrentAdvLevel">Current Adventure Level (50)</tier-attribute>
			</tier-attributes>
			<tier-keywords>
				<tier-keyword>tier_3</tier-keyword>
			</tier-keywords>
			<resources>
				<resource>
					<resource-name>New Rachival Travel Token</resource-name>
					<resource-skill>Scribing</resource-skill>
					<resource-units>1</resource-units>
					<resource-min amount="1">550</resource-min>
					<resource-opt amount="1">800</resource-opt>
				</resource>
				<resource>
					<resource-name>Azure Papyrus Sheet</resource-name>
					<resource-skill>Scribing</resource-skill>
					<resource-units>1</resource-units>
					<resource-min amount="5">550</resource-min>
					<resource-opt amount="2">800</resource-opt>
				</resource>
				<resource>
					<resource-name>Swift Feet III</resource-name>
					<resource-skill>Scribing</resource-skill>
					<resource-units>1</resource-units>
					<resource-min amount="1">550</resource-min>
					<resource-opt amount="1">800</resource-opt>
				</resource>
				<resource>
					<resource-name>Glowing Essence Orb</resource-name>
					<resource-skill>Scribing</resource-skill>
					<resource-units>1</resource-units>
					<resource-min amount="3">550</resource-min>
					<resource-opt amount="1">800</resource-opt>
				</resource>
			</resources>
		</tier>
	</item>
	<item>
		<item-name>Sslanis Travel</item-name>
		<item-icon>icon_formula_sc_01_08_11.png</item-icon>
		<item-batchqty>2</item-batchqty>
		<item-attributes>
			<item-attribute type="equipSlot">All</item-attribute>
			<item-attribute type="bulk">1</item-attribute>
			<item-attribute type="range">Self Only</item-attribute>
			<item-attribute type="recycle">30</item-attribute>
			<item-attribute type="castDelay">70</item-attribute>
			<item-attribute type="effectDescription">Teleport to a city, even with a portable cargo disk equipped.</item-attribute>
		</item-attributes>
		<item-keywords>
		</item-keywords>
		<tier>
			<tier-name>Sslanis Travel</tier-name>
			<tier-lvl name="">1</tier-lvl>
			<tier-desc>A rolled up piece of parchment, covered with strange lettering and faintly glowing runes. The parchment fairly hums with imbued power.</tier-desc>
			<tier-allowedtechniques>0</tier-allowedtechniques>
			<tier-attributes>
				<tier-attribute type="hoardValue">40</tier-attribute>
				<tier-attribute type="reqCurrentAdvLevel">Current Adventure Level (15)</tier-attribute>
			</tier-attributes>
			<tier-keywords>
				<tier-keyword>tier_1</tier-keyword>
			</tier-keywords>
			<resources>
				<resource>
					<resource-name>Sslanis Travel Token</resource-name>
					<resource-skill>Scribing</resource-skill>
					<resource-units>1</resource-units>
					<resource-min amount="1">150</resource-min>
					<resource-opt amount="1">350</resource-opt>
				</resource>
				<resource>
					<resource-name>Common Papyrus Sheet</resource-name>
					<resource-skill>Scribing</resource-skill>
					<resource-units>1</resource-units>
					<resource-min amount="5">150</resource-min>
					<resource-opt amount="2">350</resource-opt>
				</resource>
				<resource>
					<resource-name>Swift Feet I</resource-name>
					<resource-skill>Scribing</resource-skill>
					<resource-units>1</resource-units>
					<resource-min amount="1">150</resource-min>
					<resource-opt amount="1">350</resource-opt>
				</resource>
				<resource>
					<resource-name>Dim Essence Orb</resource-name>
					<resource-skill>Scribing</resource-skill>
					<resource-units>1</resource-units>
					<resource-min amount="3">150</resource-min>
					<resource-opt amount="1">350</resource-opt>
				</resource>
			</resources>
		</tier>
	</item>
</formulaset>